mcp_ankiconnect/__init__.py
mcp_ankiconnect/ankiconnect_client.py
mcp_ankiconnect/config.py
mcp_ankiconnect/main.py
mcp_ankiconnect/server.py
mcp_ankiconnect/server_prompts.py
mcp_ankiconnect-0.6.0.dist-info/METADATA
mcp_ankiconnect-0.6.0.dist-info/WHEEL
mcp_ankiconnect-0.6.0.dist-info/entry_points.txt
mcp_ankiconnect-0.6.0.dist-info/RECORD
