Metadata-Version: 2.4
Name: mcp_ankiconnect
Version: 0.6.0
Summary: Connect Claude conversations with AnkiConnect via MCP to make spaced repetition as easy as "Help me remember this"
Project-URL: repository, https://github.com/samefarrar/mcp-ankiconnect
Author-email: samefarrar <samefarrar@gmail.com>
License: MIT
Classifier: License :: OSI Approved :: MIT License
Classifier: Operating System :: OS Independent
Classifier: Programming Language :: Python :: 3
Requires-Python: >=3.11
Requires-Dist: httpx>=0.28.1
Requires-Dist: mcp[cli]>=1.2.0
Requires-Dist: pydantic>=2.10.5
Requires-Dist: uvicorn>=0.34.0
